odoo9_addon_product_brand-9.0.1.1.0-py2.7-nspkg.pth
odoo9_addon_product_brand-9.0.1.1.0.dist-info/DESCRIPTION.rst
odoo9_addon_product_brand-9.0.1.1.0.dist-info/METADATA
odoo9_addon_product_brand-9.0.1.1.0.dist-info/RECORD
odoo9_addon_product_brand-9.0.1.1.0.dist-info/WHEEL
odoo9_addon_product_brand-9.0.1.1.0.dist-info/metadata.json
odoo9_addon_product_brand-9.0.1.1.0.dist-info/namespace_packages.txt
odoo9_addon_product_brand-9.0.1.1.0.dist-info/top_level.txt
odoo_addons/product_brand/README.rst
odoo_addons/product_brand/__init__.py
odoo_addons/product_brand/__openerp__.py
odoo_addons/product_brand/i18n/es.po
odoo_addons/product_brand/i18n/fr.po
odoo_addons/product_brand/i18n/fr_FR.po
odoo_addons/product_brand/models/__init__.py
odoo_addons/product_brand/models/product_brand.py
odoo_addons/product_brand/security/ir.model.access.csv
odoo_addons/product_brand/static/description/icon.png
odoo_addons/product_brand/views/product_brand_view.xml
