Metadata-Version: 2.0
Name: odoo9-addon-product-brand
Version: 9.0.1.1.0
Summary: Product Brand Manager
Home-page: https://odoo-community.org/
Author: NetAndCo, Akretion, Prisnet Telecommunications SA, MONK Software, SerpentCS Pvt. Ltd., Odoo Community Association (OCA)
Author-email: support@odoo-community.org
License: AGPL-3
Platform: UNKNOWN
Classifier: Programming Language :: Python :: 2.7
Classifier: Framework :: Odoo
Classifier: License :: OSI Approved :: GNU Affero General Public License v3
Requires-Dist: odoo (<9.1a,>=9.0a)
